[
  {
    "rank": 13002,
    "userid": 60321,
    "ac": 100,
    "nos": 337
  },
  {
    "rank": 13003,
    "userid": 829461,
    "ac": 100,
    "nos": 337
  },
  {
    "rank": 13004,
    "userid": 175470,
    "ac": 100,
    "nos": 338
  },
  {
    "rank": 13005,
    "userid": 984465,
    "ac": 100,
    "nos": 338
  },
  {
    "rank": 13006,
    "userid": 2004447,
    "ac": 100,
    "nos": 343
  },
  {
    "rank": 13007,
    "userid": 1026853,
    "ac": 100,
    "nos": 346
  },
  {
    "rank": 13008,
    "userid": 859167,
    "ac": 100,
    "nos": 349
  },
  {
    "rank": 13009,
    "userid": 26511,
    "ac": 100,
    "nos": 351
  },
  {
    "rank": 13010,
    "userid": 930878,
    "ac": 100,
    "nos": 357
  },
  {
    "rank": 13011,
    "userid": 167557,
    "ac": 100,
    "nos": 359
  },
  {
    "rank": 13012,
    "userid": 859515,
    "ac": 100,
    "nos": 362
  },
  {
    "rank": 13013,
    "userid": 2014648,
    "ac": 100,
    "nos": 362
  },
  {
    "rank": 13014,
    "userid": 66358,
    "ac": 100,
    "nos": 365
  },
  {
    "rank": 13015,
    "userid": 15666,
    "ac": 100,
    "nos": 366
  },
  {
    "rank": 13016,
    "userid": 23088,
    "ac": 100,
    "nos": 378
  },
  {
    "rank": 13017,
    "userid": 918005,
    "ac": 100,
    "nos": 381
  },
  {
    "rank": 13018,
    "userid": 252660,
    "ac": 100,
    "nos": 391
  },
  {
    "rank": 13019,
    "userid": 1074342,
    "ac": 100,
    "nos": 393
  },
  {
    "rank": 13020,
    "userid": 20316,
    "ac": 100,
    "nos": 394
  },
  {
    "rank": 13021,
    "userid": 70084,
    "ac": 100,
    "nos": 394
  },
  {
    "rank": 13022,
    "userid": 70573,
    "ac": 100,
    "nos": 399
  },
  {
    "rank": 13023,
    "userid": 506110,
    "ac": 100,
    "nos": 401
  },
  {
    "rank": 13024,
    "userid": 881420,
    "ac": 100,
    "nos": 401
  },
  {
    "rank": 13025,
    "userid": 950584,
    "ac": 100,
    "nos": 413
  },
  {
    "rank": 13026,
    "userid": 165337,
    "ac": 100,
    "nos": 415
  },
  {
    "rank": 13027,
    "userid": 23317,
    "ac": 100,
    "nos": 418
  },
  {
    "rank": 13028,
    "userid": 68299,
    "ac": 100,
    "nos": 428
  },
  {
    "rank": 13029,
    "userid": 2007087,
    "ac": 100,
    "nos": 434
  },
  {
    "rank": 13030,
    "userid": 687,
    "ac": 100,
    "nos": 438
  },
  {
    "rank": 13031,
    "userid": 61839,
    "ac": 100,
    "nos": 445
  },
  {
    "rank": 13032,
    "userid": 2549,
    "ac": 100,
    "nos": 458
  },
  {
    "rank": 13033,
    "userid": 5357,
    "ac": 100,
    "nos": 466
  },
  {
    "rank": 13034,
    "userid": 405309,
    "ac": 100,
    "nos": 468
  },
  {
    "rank": 13035,
    "userid": 580825,
    "ac": 100,
    "nos": 472
  },
  {
    "rank": 13036,
    "userid": 710151,
    "ac": 100,
    "nos": 473
  },
  {
    "rank": 13037,
    "userid": 53999,
    "ac": 100,
    "nos": 477
  },
  {
    "rank": 13038,
    "userid": 11418,
    "ac": 100,
    "nos": 496
  },
  {
    "rank": 13039,
    "userid": 7171,
    "ac": 100,
    "nos": 518
  },
  {
    "rank": 13040,
    "userid": 946456,
    "ac": 100,
    "nos": 542
  },
  {
    "rank": 13041,
    "userid": 786197,
    "ac": 100,
    "nos": 547
  },
  {
    "rank": 13042,
    "userid": 61376,
    "ac": 100,
    "nos": 590
  },
  {
    "rank": 13043,
    "userid": 13246,
    "ac": 100,
    "nos": 640
  },
  {
    "rank": 13044,
    "userid": 2004578,
    "ac": 100,
    "nos": 643
  },
  {
    "rank": 13045,
    "userid": 786204,
    "ac": 100,
    "nos": 655
  },
  {
    "rank": 13046,
    "userid": 13235,
    "ac": 100,
    "nos": 675
  },
  {
    "rank": 13047,
    "userid": 2014848,
    "ac": 100,
    "nos": 689
  },
  {
    "rank": 13048,
    "userid": 171942,
    "ac": 100,
    "nos": 747
  },
  {
    "rank": 13049,
    "userid": 2051819,
    "ac": 100,
    "nos": 830
  },
  {
    "rank": 13050,
    "userid": 116820,
    "ac": 100,
    "nos": 879
  },
  {
    "rank": 13051,
    "userid": 2013431,
    "ac": 100,
    "nos": 897
  },
  {
    "rank": 13052,
    "userid": 64613,
    "ac": 100,
    "nos": 915
  }
]